mmtwfs/__init__.py
mmtwfs/_astropy_init.py
mmtwfs/config.py
mmtwfs/conftest.py
mmtwfs/custom_exceptions.py
mmtwfs/f9topbox.py
mmtwfs/secondary.py
mmtwfs/telescope.py
mmtwfs/utils.py
mmtwfs/version.py
mmtwfs/wfs.py
mmtwfs/zernike.py
mmtwfs/data/Surf2ActTEL_32.bin
mmtwfs/data/actuator_coordinates.dat
mmtwfs/data/bcv_node_coordinates.dat
mmtwfs/data/f5zernfield.tab
mmtwfs/data/f5zernfield_flatsurface.tab
mmtwfs/data/f5zernfield_std_curvedsurface.TXT
mmtwfs/data/f5zernfield_std_flatsurface.TXT
mmtwfs/data/mmirszernfield.tab
mmtwfs/data/null.TXT
mmtwfs/data/ref_images/LED2sec_22.fits
mmtwfs/data/ref_images/binospec_ref.fits
mmtwfs/data/ref_images/f5_hecto_ref.fits
mmtwfs/data/ref_images/f5_mask.fits
mmtwfs/data/ref_images/f9_new_ref.fits
mmtwfs/data/ref_images/f9_ref.fits
mmtwfs/data/ref_images/flwo12_mask.fits
mmtwfs/data/ref_images/flwo15_mask.fits
mmtwfs/data/ref_images/mmirs_camera1_ref.fits
mmtwfs/data/ref_images/mmirs_camera2_ref.fits
mmtwfs/data/ref_images/mmirs_mask.fits
mmtwfs/data/ref_images/newf9_mask.fits
mmtwfs/data/ref_images/oldf9_mask.fits
mmtwfs/data/test_data/1195.star.p2m18.fits
mmtwfs/data/test_data/AST45_p1000.frc
mmtwfs/data/test_data/TREX_p500_0000.fits
mmtwfs/data/test_data/auto_wfs_0037_ave.fits
mmtwfs/data/test_data/f9wfs_20200225-205600.fits
mmtwfs/data/test_data/mmirs_blank.fits
mmtwfs/data/test_data/mmirs_bogus.fits
mmtwfs/data/test_data/mmirs_wfs_0150.fits
mmtwfs/data/test_data/mmirs_wfs_rename_0566.fits
mmtwfs/data/test_data/test_newf9.fits
mmtwfs/data/test_data/wfs_ff_cal_img_2017.1113.111402.fits
mmtwfs/scripts/fix_csvs.py
mmtwfs/scripts/fix_mmirs_exposure_time.py
mmtwfs/scripts/reanalyze.py
mmtwfs/scripts/rename_mmirs_files.py
mmtwfs/tests/__init__.py
mmtwfs/tests/test_secondaries.py
mmtwfs/tests/test_telescope.py
mmtwfs/tests/test_wfs.py
mmtwfs/tests/test_zernike.py
mmtwfs-2.1.0.dist-info/AUTHORS.rst
mmtwfs-2.1.0.dist-info/LICENSE.rst
mmtwfs-2.1.0.dist-info/METADATA
mmtwfs-2.1.0.dist-info/WHEEL
mmtwfs-2.1.0.dist-info/entry_points.txt
mmtwfs-2.1.0.dist-info/top_level.txt
mmtwfs-2.1.0.dist-info/RECORD
