Metadata-Version: 2.1
Name: mmtwfs
Version: 2.1.0
Summary: Wavefront sensing and active optics management tools for the MMT Observatory
Home-page: https://github.com/MMTObservatory/mmtwfs
Author: T. E. Pickering (MMT Observatory)
Author-email: te.pickering@gmail.com
License: BSD-3
Platform: UNKNOWN
Requires-Python: >=3.8
License-File: LICENSE.rst
License-File: AUTHORS.rst
Requires-Dist: astropy
Requires-Dist: matplotlib
Requires-Dist: photutils
Requires-Dist: scikit-image
Requires-Dist: poppy
Requires-Dist: lmfit
Requires-Dist: ccdproc
Requires-Dist: astroscrappy
Requires-Dist: dnspython
Requires-Dist: parse
Requires-Dist: pytz
Requires-Dist: coloredlogs
Provides-Extra: docs
Requires-Dist: sphinx-astropy ; extra == 'docs'
Provides-Extra: extra
Requires-Dist: jupyter ; extra == 'extra'
Provides-Extra: test
Requires-Dist: tox ; extra == 'test'
Requires-Dist: pytest ; extra == 'test'
Requires-Dist: pytest-cov ; extra == 'test'
Requires-Dist: pytest-astropy ; extra == 'test'
Requires-Dist: nose ; extra == 'test'
Requires-Dist: coverage ; extra == 'test'
Requires-Dist: codecov ; extra == 'test'
